bouncing_decayer_optimizer/__init__.py
bouncing_decayer_optimizer-1.0.0.dist-info/licenses/LICENSE
bouncing_decayer_optimizer-1.0.0.dist-info/METADATA
bouncing_decayer_optimizer-1.0.0.dist-info/WHEEL
bouncing_decayer_optimizer-1.0.0.dist-info/top_level.txt
bouncing_decayer_optimizer-1.0.0.dist-info/RECORD
