Metadata-Version: 2.4
Name: bouncing-decayer-optimizer
Version: 1.0.0
Summary: A physics-inspired optimizer adding decaying oscillations to gradient descent
Author-email: Sanskar <sawanesanskar07@gmail.com>
License: MIT License
Project-URL: Homepage, https://github.com/sandy1279/bouncing_decayer_optimizer
Project-URL: Repository, https://github.com/sandy1279/bouncing_decayer_optimizer
Keywords: optimizer,deep learning,physics-inspired,gradient descent,pytorch
Requires-Python: >=3.7
License-File: LICENSE
Requires-Dist: torch>=1.7
Dynamic: license-file
